pain001/__init__.py
pain001/__main__.py
pain001/api/__init__.py
pain001/api/app.py
pain001/api/job_manager.py
pain001/api/models.py
pain001/cli/__init__.py
pain001/cli/cli.py
pain001/constants.py
pain001/context/__init__.py
pain001/context/context.py
pain001/core/__init__.py
pain001/core/core.py
pain001/csv/__init__.py
pain001/csv/load_csv_data.py
pain001/csv/validate_csv_data.py
pain001/data/__init__.py
pain001/data/loader.py
pain001/db/__init__.py
pain001/db/load_db_data.py
pain001/db/load_db_data_streaming.py
pain001/db/validate_db_data.py
pain001/exceptions.py
pain001/json/__init__.py
pain001/json/load_json_data.py
pain001/logging_schema.py
pain001/parquet/__init__.py
pain001/parquet/load_parquet_data.py
pain001/schemas/__init__.py
pain001/schemas/pain.001.001.03.schema.json
pain001/schemas/pain.001.001.04.schema.json
pain001/schemas/pain.001.001.05.schema.json
pain001/schemas/pain.001.001.06.schema.json
pain001/schemas/pain.001.001.07.schema.json
pain001/schemas/pain.001.001.08.schema.json
pain001/schemas/pain.001.001.09.schema.json
pain001/schemas/pain.001.001.10.schema.json
pain001/schemas/pain.001.001.11.schema.json
pain001/security/__init__.py
pain001/security/path_validator.py
pain001/templates/__init__.py
pain001/templates/pain.001.001.03/__init__.py
pain001/templates/pain.001.001.03/pain.001.001.03.xml
pain001/templates/pain.001.001.03/pain.001.001.03.xsd
pain001/templates/pain.001.001.03/template.csv
pain001/templates/pain.001.001.03/template.db
pain001/templates/pain.001.001.03/template.xml
pain001/templates/pain.001.001.04/__init__.py
pain001/templates/pain.001.001.04/pain.001.001.04.xml
pain001/templates/pain.001.001.04/pain.001.001.04.xsd
pain001/templates/pain.001.001.04/template.csv
pain001/templates/pain.001.001.04/template.db
pain001/templates/pain.001.001.04/template.xml
pain001/templates/pain.001.001.05/__init__.py
pain001/templates/pain.001.001.05/pain.001.001.05.xml
pain001/templates/pain.001.001.05/pain.001.001.05.xsd
pain001-0.0.47.dist-info/METADATA
pain001-0.0.47.dist-info/WHEEL
pain001-0.0.47.dist-info/entry_points.txt
pain001-0.0.47.dist-info/licenses/LICENSE-APACHE
pain001-0.0.47.dist-info/licenses/LICENSE-MIT
pain001-0.0.47.dist-info/RECORD
