Metadata-Version: 2.4
Name: pain001
Version: 0.0.47
Summary: Pain001 is a Python Library for Automating ISO 20022-Compliant Payment Files Using CSV Data.
License: Apache-2.0
License-File: LICENSE-APACHE
License-File: LICENSE-MIT
Author: Sebastien Rousseau
Author-email: sebastian.rousseau@gmail.com
Requires-Python: >=3.9.2,<4.0.0
Classifier: License :: OSI Approved :: Apache Software License
Classifier: Programming Language :: Python :: 3
Classifier: Programming Language :: Python :: 3.10
Classifier: Programming Language :: Python :: 3.11
Classifier: Programming Language :: Python :: 3.12
Classifier: Programming Language :: Python :: 3.13
Classifier: Programming Language :: Python :: 3.14
Requires-Dist: click (==8.1.7)
Requires-Dist: colorama (==0.4.6)
Requires-Dist: cryptography (>=44.0.1,<47.0.0)
Requires-Dist: defusedxml (==0.7.1)
Requires-Dist: fastapi (>=0.95)
Requires-Dist: httpx (>=0.23)
Requires-Dist: jinja2 (==3.1.6)
Requires-Dist: jsonschema (>=4.17,<4.18)
Requires-Dist: markupsafe (==2.1.5)
Requires-Dist: pyarrow (>=18.0.0,<19.0.0)
Requires-Dist: pygments (==2.18.0)
Requires-Dist: rich (==13.7.1)
Requires-Dist: uvicorn[standard] (>=0.20)
Requires-Dist: xmlschema (>=3.4.0,<4.0.0)
Project-URL: Homepage, https://pain001.com
Project-URL: Repository, https://github.com/sebastienrousseau/pain001
